pytabtex/Table.py
pytabtex/__init__.py
pytabtex-0.1.3.dist-info/LICENSE
pytabtex-0.1.3.dist-info/METADATA
pytabtex-0.1.3.dist-info/WHEEL
pytabtex-0.1.3.dist-info/top_level.txt
pytabtex-0.1.3.dist-info/RECORD
