Metadata-Version: 2.1
Name: pytabtex
Version: 0.1.3
Summary: Use simple python to create custom latex tables
Author-email: Nour Oulad Moussa <nourom.professional@gmail.com>
Project-URL: Homepage, https://github.com/NourOM02/pytabtex
Project-URL: Issues, https://github.com/NourOM02/pytabtex/issues
Classifier: Programming Language :: Python :: 3
Classifier: License :: OSI Approved :: MIT License
Classifier: Operating System :: OS Independent
Requires-Python: >=3.8
License-File: LICENSE
Requires-Dist: pandas
